llama_index/postprocessor/flag_embedding_reranker/__init__.py
llama_index/postprocessor/flag_embedding_reranker/base.py
llama_index_postprocessor_flag_embedding_reranker-0.4.1.dist-info/METADATA
llama_index_postprocessor_flag_embedding_reranker-0.4.1.dist-info/WHEEL
llama_index_postprocessor_flag_embedding_reranker-0.4.1.dist-info/licenses/LICENSE
llama_index_postprocessor_flag_embedding_reranker-0.4.1.dist-info/RECORD
